py_GameUI/__init__.py
py_GameUI-1.0.8.dist-info/LICENSE
py_GameUI-1.0.8.dist-info/METADATA
py_GameUI-1.0.8.dist-info/WHEEL
py_GameUI-1.0.8.dist-info/top_level.txt
py_GameUI-1.0.8.dist-info/RECORD
