Metadata-Version: 2.1
Name: py-GameUI
Version: 1.0.8
Summary: A simple GUI library for pygame
Home-page: UNKNOWN
Author: Nolawz
Author-email: nolawz46@gmail.com
License: MIT
Project-URL: Documentation, https://aman333nolawz.github.io/py-GameUI/
Project-URL: Bug Tracker, https://github.com/aman333nolawz/py-GameUI/issues
Project-URL: Source, https://github.com/aman333nolawz/py-GameUI/
Keywords: python,pygame,pygame gui,py-GameUI,gui pygame,gui package for pygame
Platform: UNKNOWN
Classifier: Development Status :: 1 - Planning
Classifier: Intended Audience :: Developers
Classifier: Programming Language :: Python :: 3
Classifier: Operating System :: Unix
Classifier: Operating System :: MacOS :: MacOS X
Classifier: Operating System :: Microsoft :: Windows
License-File: LICENSE
Requires-Dist: pygame
